{
	"format": "BeepBox",
	"version": 9,
	"scale": "normal :)",
	"key": "C",
	"introBars": 0,
	"loopBars": 16,
	"beatsPerBar": 8,
	"ticksPerBeat": 4,
	"beatsPerMinute": 240,
	"layeredInstruments": false,
	"patternInstruments": false,
	"channels": [
		{
			"type": "pitch",
			"instruments": [
				{
					"type": "chip",
					"volume": 20,
					"eqFilter": [
						{
							"type": "low-pass",
							"cutoffHz": 6727.17,
							"linearGain": 1
						}
					],
					"effects": [
						"vibrato"
					],
					"vibrato": "light",
					"fadeInSeconds": 0.0125,
					"fadeOutTicks": 12,
					"wave": "sawtooth",
					"unison": "hum",
					"envelopes": []
				}
			],
			"patterns": [
				{
					"notes": [
						{
							"pitches": [
								60
							],
							"points": [
								{
									"tick": 0,
									"pitchBend": 0,
									"volume": 100
								},
								{
									"tick": 4,
									"pitchBend": 0,
									"volume": 100
								}
							],
							"continuesLastPattern": false
						},
						{
							"pitches": [
								62
							],
							"points": [
								{
									"tick": 4,
									"pitchBend": 0,
									"volume": 100
								},
								{
									"tick": 8,
									"pitchBend": 0,
									"volume": 100
								}
							]
						},
						{
							"pitches": [
								62
							],
							"points": [
								{
									"tick": 8,
									"pitchBend": 0,
									"volume": 100
								},
								{
									"tick": 12,
									"pitchBend": 0,
									"volume": 100
								}
							]
						},
						{
							"pitches": [
								60
							],
							"points": [
								{
									"tick": 12,
									"pitchBend": 0,
									"volume": 100
								},
								{
									"tick": 16,
									"pitchBend": 0,
									"volume": 100
								}
							]
						},
						{
							"pitches": [
								60
							],
							"points": [
								{
									"tick": 20,
									"pitchBend": 0,
									"volume": 100
								},
								{
									"tick": 24,
									"pitchBend": 0,
									"volume": 100
								}
							]
						},
						{
							"pitches": [
								62
							],
							"points": [
								{
									"tick": 24,
									"pitchBend": 0,
									"volume": 100
								},
								{
									"tick": 28,
									"pitchBend": 0,
									"volume": 100
								}
							]
						},
						{
							"pitches": [
								60
							],
							"points": [
								{
									"tick": 28,
									"pitchBend": 0,
									"volume": 100
								},
								{
									"tick": 32,
									"pitchBend": 0,
									"volume": 100
								}
							]
						}
					]
				},
				{
					"notes": [
						{
							"pitches": [
								60
							],
							"points": [
								{
									"tick": 0,
									"pitchBend": 0,
									"volume": 100
								},
								{
									"tick": 4,
									"pitchBend": 0,
									"volume": 100
								}
							],
							"continuesLastPattern": false
						},
						{
							"pitches": [
								62
							],
							"points": [
								{
									"tick": 4,
									"pitchBend": 0,
									"volume": 100
								},
								{
									"tick": 8,
									"pitchBend": 0,
									"volume": 100
								}
							]
						},
						{
							"pitches": [
								62
							],
							"points": [
								{
									"tick": 8,
									"pitchBend": 0,
									"volume": 100
								},
								{
									"tick": 12,
									"pitchBend": 0,
									"volume": 100
								}
							]
						},
						{
							"pitches": [
								64
							],
							"points": [
								{
									"tick": 12,
									"pitchBend": 0,
									"volume": 100
								},
								{
									"tick": 16,
									"pitchBend": 0,
									"volume": 100
								}
							]
						},
						{
							"pitches": [
								60
							],
							"points": [
								{
									"tick": 20,
									"pitchBend": 0,
									"volume": 100
								},
								{
									"tick": 24,
									"pitchBend": 0,
									"volume": 100
								}
							]
						},
						{
							"pitches": [
								62
							],
							"points": [
								{
									"tick": 24,
									"pitchBend": 0,
									"volume": 100
								},
								{
									"tick": 28,
									"pitchBend": 0,
									"volume": 100
								}
							]
						},
						{
							"pitches": [
								64
							],
							"points": [
								{
									"tick": 28,
									"pitchBend": 0,
									"volume": 100
								},
								{
									"tick": 32,
									"pitchBend": 0,
									"volume": 100
								}
							]
						}
					]
				},
				{
					"notes": [
						{
							"pitches": [
								64
							],
							"points": [
								{
									"tick": 0,
									"pitchBend": 0,
									"volume": 100
								},
								{
									"tick": 4,
									"pitchBend": 0,
									"volume": 100
								}
							],
							"continuesLastPattern": false
						},
						{
							"pitches": [
								62
							],
							"points": [
								{
									"tick": 4,
									"pitchBend": 0,
									"volume": 100
								},
								{
									"tick": 8,
									"pitchBend": 0,
									"volume": 100
								}
							]
						},
						{
							"pitches": [
								62
							],
							"points": [
								{
									"tick": 8,
									"pitchBend": 0,
									"volume": 100
								},
								{
									"tick": 12,
									"pitchBend": 0,
									"volume": 100
								}
							]
						},
						{
							"pitches": [
								60
							],
							"points": [
								{
									"tick": 12,
									"pitchBend": 0,
									"volume": 100
								},
								{
									"tick": 16,
									"pitchBend": 0,
									"volume": 100
								}
							]
						},
						{
							"pitches": [
								64
							],
							"points": [
								{
									"tick": 20,
									"pitchBend": 0,
									"volume": 100
								},
								{
									"tick": 24,
									"pitchBend": 0,
									"volume": 100
								}
							]
						},
						{
							"pitches": [
								62
							],
							"points": [
								{
									"tick": 24,
									"pitchBend": 0,
									"volume": 100
								},
								{
									"tick": 28,
									"pitchBend": 0,
									"volume": 100
								}
							]
						},
						{
							"pitches": [
								60
							],
							"points": [
								{
									"tick": 28,
									"pitchBend": 0,
									"volume": 100
								},
								{
									"tick": 32,
									"pitchBend": 0,
									"volume": 100
								}
							]
						}
					]
				},
				{
					"notes": []
				},
				{
					"notes": []
				},
				{
					"notes": []
				},
				{
					"notes": []
				},
				{
					"notes": []
				}
			],
			"sequence": [
				1,
				1,
				1,
				1,
				1,
				1,
				1,
				1,
				1,
				1,
				2,
				3,
				2,
				3,
				2,
				3
			],
			"octaveScrollBar": 3
		},
		{
			"type": "pitch",
			"instruments": [
				{
					"type": "chip",
					"volume": 40,
					"eqFilter": [],
					"effects": [
						"transition type"
					],
					"transition": "interrupt",
					"fadeInSeconds": 0,
					"fadeOutTicks": -1,
					"wave": "sawtooth",
					"unison": "none",
					"envelopes": []
				}
			],
			"patterns": [
				{
					"notes": [
						{
							"pitches": [
								52,
								55
							],
							"points": [
								{
									"tick": 0,
									"pitchBend": 0,
									"volume": 100
								},
								{
									"tick": 8,
									"pitchBend": 0,
									"volume": 100
								},
								{
									"tick": 16,
									"pitchBend": 0,
									"volume": 33
								}
							],
							"continuesLastPattern": false
						},
						{
							"pitches": [
								55,
								52
							],
							"points": [
								{
									"tick": 20,
									"pitchBend": 0,
									"volume": 100
								},
								{
									"tick": 32,
									"pitchBend": 0,
									"volume": 100
								}
							]
						}
					]
				},
				{
					"notes": [
						{
							"pitches": [
								53,
								57
							],
							"points": [
								{
									"tick": 0,
									"pitchBend": 0,
									"volume": 100
								},
								{
									"tick": 8,
									"pitchBend": 0,
									"volume": 100
								},
								{
									"tick": 16,
									"pitchBend": 0,
									"volume": 33
								}
							],
							"continuesLastPattern": false
						},
						{
							"pitches": [
								57,
								53
							],
							"points": [
								{
									"tick": 20,
									"pitchBend": 0,
									"volume": 100
								},
								{
									"tick": 32,
									"pitchBend": 0,
									"volume": 100
								}
							]
						}
					]
				},
				{
					"notes": [
						{
							"pitches": [
								57,
								60
							],
							"points": [
								{
									"tick": 0,
									"pitchBend": 0,
									"volume": 100
								},
								{
									"tick": 8,
									"pitchBend": 0,
									"volume": 100
								},
								{
									"tick": 16,
									"pitchBend": 0,
									"volume": 33
								}
							],
							"continuesLastPattern": false
						},
						{
							"pitches": [
								60,
								57
							],
							"points": [
								{
									"tick": 20,
									"pitchBend": 0,
									"volume": 100
								},
								{
									"tick": 32,
									"pitchBend": 0,
									"volume": 100
								}
							]
						}
					]
				},
				{
					"notes": [
						{
							"pitches": [
								55,
								59
							],
							"points": [
								{
									"tick": 0,
									"pitchBend": 0,
									"volume": 100
								},
								{
									"tick": 8,
									"pitchBend": 0,
									"volume": 100
								},
								{
									"tick": 16,
									"pitchBend": 0,
									"volume": 33
								}
							],
							"continuesLastPattern": false
						},
						{
							"pitches": [
								59,
								55
							],
							"points": [
								{
									"tick": 20,
									"pitchBend": 0,
									"volume": 100
								},
								{
									"tick": 32,
									"pitchBend": 0,
									"volume": 100
								}
							]
						}
					]
				},
				{
					"notes": []
				},
				{
					"notes": []
				},
				{
					"notes": []
				},
				{
					"notes": []
				}
			],
			"sequence": [
				0,
				0,
				1,
				2,
				3,
				4,
				1,
				2,
				3,
				4,
				1,
				2,
				3,
				4,
				0,
				0
			],
			"octaveScrollBar": 2
		},
		{
			"type": "pitch",
			"instruments": [
				{
					"type": "chip",
					"volume": 100,
					"eqFilter": [
						{
							"type": "low-pass",
							"cutoffHz": 4000,
							"linearGain": 2
						}
					],
					"effects": [
						"vibrato",
						"chorus",
						"reverb"
					],
					"vibrato": "none",
					"chorus": 100,
					"reverb": 33,
					"fadeInSeconds": 0.0125,
					"fadeOutTicks": 72,
					"wave": "rounded",
					"unison": "hum",
					"envelopes": []
				}
			],
			"patterns": [
				{
					"notes": [
						{
							"pitches": [
								24
							],
							"points": [
								{
									"tick": 0,
									"pitchBend": 0,
									"volume": 100
								},
								{
									"tick": 16,
									"pitchBend": 0,
									"volume": 100
								}
							],
							"continuesLastPattern": false
						},
						{
							"pitches": [
								24
							],
							"points": [
								{
									"tick": 20,
									"pitchBend": 0,
									"volume": 100
								},
								{
									"tick": 32,
									"pitchBend": 0,
									"volume": 100
								}
							]
						}
					]
				},
				{
					"notes": [
						{
							"pitches": [
								26
							],
							"points": [
								{
									"tick": 0,
									"pitchBend": 0,
									"volume": 100
								},
								{
									"tick": 16,
									"pitchBend": 0,
									"volume": 100
								}
							],
							"continuesLastPattern": false
						},
						{
							"pitches": [
								26
							],
							"points": [
								{
									"tick": 20,
									"pitchBend": 0,
									"volume": 100
								},
								{
									"tick": 32,
									"pitchBend": 0,
									"volume": 100
								}
							]
						}
					]
				},
				{
					"notes": [
						{
							"pitches": [
								29
							],
							"points": [
								{
									"tick": 0,
									"pitchBend": 0,
									"volume": 100
								},
								{
									"tick": 16,
									"pitchBend": 0,
									"volume": 100
								}
							],
							"continuesLastPattern": false
						},
						{
							"pitches": [
								29
							],
							"points": [
								{
									"tick": 20,
									"pitchBend": 0,
									"volume": 100
								},
								{
									"tick": 32,
									"pitchBend": 0,
									"volume": 100
								}
							]
						}
					]
				},
				{
					"notes": [
						{
							"pitches": [
								28
							],
							"points": [
								{
									"tick": 0,
									"pitchBend": 0,
									"volume": 100
								},
								{
									"tick": 16,
									"pitchBend": 0,
									"volume": 100
								}
							],
							"continuesLastPattern": false
						},
						{
							"pitches": [
								28
							],
							"points": [
								{
									"tick": 20,
									"pitchBend": 0,
									"volume": 100
								},
								{
									"tick": 32,
									"pitchBend": 0,
									"volume": 100
								}
							]
						}
					]
				},
				{
					"notes": [
						{
							"pitches": [
								24,
								21
							],
							"points": [
								{
									"tick": 0,
									"pitchBend": 0,
									"volume": 100
								},
								{
									"tick": 16,
									"pitchBend": 0,
									"volume": 100
								}
							],
							"continuesLastPattern": false
						},
						{
							"pitches": [
								24,
								21
							],
							"points": [
								{
									"tick": 20,
									"pitchBend": 0,
									"volume": 100
								},
								{
									"tick": 32,
									"pitchBend": 0,
									"volume": 100
								}
							]
						}
					]
				},
				{
					"notes": [
						{
							"pitches": [
								26,
								21
							],
							"points": [
								{
									"tick": 0,
									"pitchBend": 0,
									"volume": 100
								},
								{
									"tick": 16,
									"pitchBend": 0,
									"volume": 100
								}
							],
							"continuesLastPattern": false
						},
						{
							"pitches": [
								26,
								21
							],
							"points": [
								{
									"tick": 20,
									"pitchBend": 0,
									"volume": 100
								},
								{
									"tick": 32,
									"pitchBend": 0,
									"volume": 100
								}
							]
						}
					]
				},
				{
					"notes": [
						{
							"pitches": [
								29,
								24
							],
							"points": [
								{
									"tick": 0,
									"pitchBend": 0,
									"volume": 100
								},
								{
									"tick": 16,
									"pitchBend": 0,
									"volume": 100
								}
							],
							"continuesLastPattern": false
						},
						{
							"pitches": [
								29,
								24
							],
							"points": [
								{
									"tick": 20,
									"pitchBend": 0,
									"volume": 100
								},
								{
									"tick": 32,
									"pitchBend": 0,
									"volume": 100
								}
							]
						}
					]
				},
				{
					"notes": [
						{
							"pitches": [
								28,
								23
							],
							"points": [
								{
									"tick": 0,
									"pitchBend": 0,
									"volume": 100
								},
								{
									"tick": 16,
									"pitchBend": 0,
									"volume": 100
								}
							],
							"continuesLastPattern": false
						},
						{
							"pitches": [
								28,
								23
							],
							"points": [
								{
									"tick": 20,
									"pitchBend": 0,
									"volume": 100
								},
								{
									"tick": 32,
									"pitchBend": 0,
									"volume": 100
								}
							]
						}
					]
				}
			],
			"sequence": [
				0,
				0,
				1,
				2,
				3,
				4,
				1,
				2,
				3,
				4,
				5,
				6,
				7,
				8,
				0,
				0
			],
			"octaveScrollBar": 1
		},
		{
			"type": "drum",
			"instruments": [
				{
					"type": "spectrum",
					"volume": 40,
					"eqFilter": [],
					"effects": [],
					"fadeInSeconds": 0,
					"fadeOutTicks": 6,
					"spectrum": [
						100,
						100,
						100,
						100,
						100,
						100,
						100,
						100,
						100,
						100,
						100,
						100,
						100,
						100,
						100,
						100,
						100,
						100,
						100,
						100,
						100,
						100,
						100,
						100,
						100,
						100,
						100,
						100,
						100,
						100
					],
					"envelopes": []
				}
			],
			"patterns": [
				{
					"notes": [
						{
							"pitches": [
								5
							],
							"points": [
								{
									"tick": 0,
									"pitchBend": 0,
									"volume": 100
								},
								{
									"tick": 4,
									"pitchBend": 0,
									"volume": 0
								}
							],
							"continuesLastPattern": false
						},
						{
							"pitches": [
								5
							],
							"points": [
								{
									"tick": 4,
									"pitchBend": 0,
									"volume": 100
								},
								{
									"tick": 8,
									"pitchBend": 0,
									"volume": 0
								}
							]
						},
						{
							"pitches": [
								6
							],
							"points": [
								{
									"tick": 8,
									"pitchBend": 0,
									"volume": 100
								},
								{
									"tick": 12,
									"pitchBend": 0,
									"volume": 0
								}
							]
						},
						{
							"pitches": [
								5
							],
							"points": [
								{
									"tick": 12,
									"pitchBend": 0,
									"volume": 100
								},
								{
									"tick": 16,
									"pitchBend": 0,
									"volume": 0
								}
							]
						},
						{
							"pitches": [
								5
							],
							"points": [
								{
									"tick": 20,
									"pitchBend": 0,
									"volume": 100
								},
								{
									"tick": 24,
									"pitchBend": 0,
									"volume": 0
								}
							]
						},
						{
							"pitches": [
								6
							],
							"points": [
								{
									"tick": 24,
									"pitchBend": 0,
									"volume": 100
								},
								{
									"tick": 28,
									"pitchBend": 0,
									"volume": 0
								}
							]
						},
						{
							"pitches": [
								5
							],
							"points": [
								{
									"tick": 28,
									"pitchBend": 0,
									"volume": 100
								},
								{
									"tick": 32,
									"pitchBend": 0,
									"volume": 0
								}
							]
						}
					]
				},
				{
					"notes": [
						{
							"pitches": [
								5
							],
							"points": [
								{
									"tick": 0,
									"pitchBend": 0,
									"volume": 100
								},
								{
									"tick": 4,
									"pitchBend": 0,
									"volume": 0
								}
							],
							"continuesLastPattern": false
						},
						{
							"pitches": [
								5,
								10
							],
							"points": [
								{
									"tick": 4,
									"pitchBend": 0,
									"volume": 100
								},
								{
									"tick": 8,
									"pitchBend": 0,
									"volume": 0
								}
							]
						},
						{
							"pitches": [
								6
							],
							"points": [
								{
									"tick": 8,
									"pitchBend": 0,
									"volume": 100
								},
								{
									"tick": 12,
									"pitchBend": 0,
									"volume": 0
								}
							]
						},
						{
							"pitches": [
								5,
								10
							],
							"points": [
								{
									"tick": 12,
									"pitchBend": 0,
									"volume": 100
								},
								{
									"tick": 16,
									"pitchBend": 0,
									"volume": 0
								}
							]
						},
						{
							"pitches": [
								5,
								10
							],
							"points": [
								{
									"tick": 20,
									"pitchBend": 0,
									"volume": 100
								},
								{
									"tick": 24,
									"pitchBend": 0,
									"volume": 0
								}
							]
						},
						{
							"pitches": [
								6
							],
							"points": [
								{
									"tick": 24,
									"pitchBend": 0,
									"volume": 100
								},
								{
									"tick": 28,
									"pitchBend": 0,
									"volume": 0
								}
							]
						},
						{
							"pitches": [
								5,
								10
							],
							"points": [
								{
									"tick": 28,
									"pitchBend": 0,
									"volume": 100
								},
								{
									"tick": 32,
									"pitchBend": 0,
									"volume": 0
								}
							]
						}
					]
				},
				{
					"notes": []
				},
				{
					"notes": []
				},
				{
					"notes": []
				},
				{
					"notes": []
				},
				{
					"notes": []
				},
				{
					"notes": []
				}
			],
			"sequence": [
				1,
				1,
				1,
				1,
				1,
				1,
				2,
				2,
				2,
				2,
				2,
				2,
				2,
				2,
				2,
				1
			]
		}
	]
}